[
  {
    "piece": "S",
    "cleared": 0,
    "review": "Optimal",
    "search_mode": "beam",
    "weights": [
      0.45,
      0.95,
      0.3,
      1.15
    ],
    "score": 10,
    "snapshot": [
      "..........",
      "..........",
      "..........",
      "..........",
      "..........",
      "..........",
      "..##......",
      ".##......."
    ],
    "ts": 1776776027
  },
  {
    "piece": "T",
    "cleared": 0,
    "review": "Optimal",
    "search_mode": "beam",
    "weights": [
      0.45,
      0.95,
      0.3,
      1.15
    ],
    "score": 42,
    "snapshot": [
      "..........",
      "..........",
      "..........",
      "..........",
      "..........",
      "#.........",
      "####......",
      "###......."
    ],
    "ts": 1776776029
  },
  {
    "piece": "I",
    "cleared": 0,
    "review": "Optimal",
    "search_mode": "beam",
    "weights": [
      0.45,
      0.95,
      0.3,
      1.15
    ],
    "score": 76,
    "snapshot": [
      "..........",
      "..........",
      "..........",
      "..........",
      "..........",
      "#.........",
      "####......",
      "###...####"
    ],
    "ts": 1776776031
  },
  {
    "piece": "O",
    "cleared": 0,
    "review": "Optimal",
    "search_mode": "beam",
    "weights": [
      0.45,
      0.95,
      0.3,
      1.15
    ],
    "score": 110,
    "snapshot": [
      "..........",
      "..........",
      "..........",
      "..........",
      "..........",
      "#.........",
      "######....",
      "###.######"
    ],
    "ts": 1776776033
  },
  {
    "piece": "S",
    "cleared": 1,
    "review": "Optimal",
    "search_mode": "beam",
    "weights": [
      0.45,
      0.95,
      0.3,
      1.15
    ],
    "score": 600,
    "snapshot": [
      "..........",
      "..........",
      "..........",
      ".....#....",
      ".....#....",
      ".....#....",
      "#....#....",
      "##.#######"
    ],
    "ts": 1776776058
  },
  {
    "piece": "Z",
    "cleared": 1,
    "review": "Optimal",
    "search_mode": "beam",
    "weights": [
      0.45,
      0.95,
      0.3,
      1.15
    ],
    "score": 730,
    "snapshot": [
      "..........",
      "..........",
      "..........",
      "..........",
      ".....#....",
      ".....#....",
      "...#.#....",
      "#.##.#...."
    ],
    "ts": 1776776060
  },
  {
    "piece": "Z",
    "cleared": 1,
    "review": "Optimal",
    "search_mode": "beam",
    "weights": [
      0.45,
      0.95,
      0.3,
      1.15
    ],
    "score": 1104,
    "snapshot": [
      "..........",
      "..........",
      "..........",
      "..........",
      "..........",
      "...##.....",
      "...###.#..",
      "...#####.#"
    ],
    "ts": 1776776077
  },
  {
    "piece": "J",
    "cleared": 0,
    "review": "Optimal",
    "search_mode": "beam",
    "weights": [
      0.45,
      0.95,
      0.3,
      1.15
    ],
    "score": 1132,
    "snapshot": [
      "..........",
      "..........",
      "..........",
      "..........",
      "...###....",
      "...###....",
      "...###.#..",
      "...#####.#"
    ],
    "ts": 1776776080
  },
  {
    "piece": "S",
    "cleared": 0,
    "review": "Blunder",
    "search_mode": "beam",
    "weights": [
      0.45,
      0.95,
      0.3,
      1.15
    ],
    "score": 1504,
    "snapshot": [
      "..........",
      "..........",
      "..........",
      "..........",
      ".....##...",
      "....###...",
      "...######.",
      ".#########"
    ],
    "ts": 1776776097
  },
  {
    "piece": "J",
    "cleared": 0,
    "review": "Blunder",
    "search_mode": "beam",
    "weights": [
      0.45,
      0.95,
      0.3,
      1.15
    ],
    "score": 1532,
    "snapshot": [
      "..........",
      "..........",
      "..........",
      "..........",
      ".....##...",
      "....######",
      "...#######",
      ".#########"
    ],
    "ts": 1776776100
  },
  {
    "piece": "L",
    "cleared": 2,
    "review": "Optimal",
    "search_mode": "beam",
    "weights": [
      0.45,
      0.95,
      0.3,
      1.15
    ],
    "score": 1864,
    "snapshot": [
      "..........",
      "..........",
      "..........",
      "..........",
      "..........",
      "..........",
      ".....##...",
      "....######"
    ],
    "ts": 1776776102
  },
  {
    "piece": "I",
    "cleared": 1,
    "review": "Optimal",
    "search_mode": "beam",
    "weights": [
      0.45,
      0.95,
      0.3,
      1.15
    ],
    "score": 2098,
    "snapshot": [
      "..........",
      "..........",
      "..........",
      "..........",
      "..........",
      "..........",
      "..........",
      ".....##..."
    ],
    "ts": 1776776105
  },
  {
    "piece": "I",
    "cleared": 0,
    "review": "Optimal",
    "search_mode": "beam",
    "weights": [
      0.45,
      0.95,
      0.3,
      1.15
    ],
    "score": 2126,
    "snapshot": [
      "..........",
      "..........",
      "..........",
      "..........",
      "..........",
      "..........",
      "..........",
      ".######..."
    ],
    "ts": 1776776109
  }
]